FALL/__init__.py
FALL/__main__.py
FALL/core/LFI.py
FALL/core/__init__.py
FALL/core/clear.py
FALL/core/crawler.py
FALL/core/dirbrute.py
FALL/core/displayoptions.py
FALL/core/encoder.py
FALL/core/exit.py
FALL/core/openred.py
FALL/core/port_scanner.py
FALL/core/reversegen.py
FALL/core/subenum.py
FALL/db/Common_Subdomains-wordlist.txt
FALL/db/Critical_file_2_wordlist.txt
FALL/db/Critical_file_wordlist.txt
FALL/db/LFI_Payloads.txt
FALL/db/Open_redirect_payloads.txt
FALL/db/Short_Subdomains-wordlist.txt
FALL/db/big_subdomains-wordlist.txt
FALL/db/dirbrute_wordlist.txt
FALL-1.8.dist-info/LICENSE.md
FALL-1.8.dist-info/METADATA
FALL-1.8.dist-info/WHEEL
FALL-1.8.dist-info/entry_points.txt
FALL-1.8.dist-info/top_level.txt
FALL-1.8.dist-info/RECORD
