Metadata-Version: 2.1
Name: FALL
Version: 1.8
Summary: A automated penetration testing tool
Home-page: https://github.com/DevanshRaghav75/FALL
Author: Devansh Raghav
Author-email: indiananonymous75@gmail.com
License: MIT
Keywords: FALL,Bug Bounty,pentesting,security,hacking
Platform: UNKNOWN
Classifier: Intended Audience :: Developers
Classifier: Intended Audience :: Information Technology
Classifier: Topic :: Security
Classifier: License :: OSI Approved :: MIT License
Classifier: Programming Language :: Python
Requires-Dist: bs4
Requires-Dist: colorama
Requires-Dist: emoji
Requires-Dist: requests
